<ingredientes>
    <ingrediente id="1">
        <name>Pan</name>
        <price>3.15</price>
    </ingrediente>
    <ingrediente id="2">
        <name>Lechuga</name>
        <price>1.74</price>
    </ingrediente>
    <ingrediente id="3">
        <name>Queso</name>
        <price>3.72</price>
    </ingrediente>
    <ingrediente id="4">
        <name>Carne</name>
        <price>4.06</price>
    </ingrediente>
    <ingrediente id="5">
        <name>Cebolla</name>
        <price>2.86</price>
    </ingrediente>
    <ingrediente id="6">
        <name>Ketchup</name>
        <price>4.94</price>
    </ingrediente>
    <ingrediente id="7">
        <name>Pepinillo</name>
        <price>3.66</price>
    </ingrediente>
</ingredientes>